flexenv/__init__.py
flexenv-0.1.2.dist-info/LICENSE
flexenv-0.1.2.dist-info/METADATA
flexenv-0.1.2.dist-info/WHEEL
flexenv-0.1.2.dist-info/top_level.txt
flexenv-0.1.2.dist-info/RECORD
